{
 "schema": 2,
 "anchor": "2026-07-14 02:00:00+00:00",
 "last_bar": "2026-07-14 01:00:00+00:00",
 "equity": 8783.88541320898,
 "carry": {
  "cash": 8783.88541320898,
  "peak": 10062.036468248654,
  "dd_frozen": false,
  "circuit_until": "2026-07-14 19:00:00+00:00",
  "loss_log": [
   [
    "2026-07-13 03:00:00+00:00",
    1216.114586791019
   ]
  ],
  "cooldown": {},
  "positions": {},
  "pendings": []
 },
 "pages": {},
 "closed_keys": [
  "SOL|2026-07-12 15:00:00+00:00"
 ],
 "last_run": "2026-07-14 02:03:45.085031+00:00"
}